daft/.ruff.toml
daft/__init__.py
daft/ai/__init__.py
daft/ai/_expressions.py
daft/ai/google/__init__.py
daft/ai/google/protocols/__init__.py
daft/ai/google/protocols/prompter.py
daft/ai/google/provider.py
daft/ai/google/typing.py
daft/ai/lm_studio/__init__.py
daft/ai/lm_studio/protocols/text_embedder.py
daft/ai/lm_studio/provider.py
daft/ai/metrics.py
daft/ai/openai/__init__.py
daft/ai/openai/protocols/__init__.py
daft/ai/openai/protocols/prompter.py
daft/ai/openai/protocols/text_embedder.py
daft/ai/openai/provider.py
daft/ai/openai/typing.py
daft/ai/protocols.py
daft/ai/provider.py
daft/ai/transformers/__init__.py
daft/ai/transformers/protocols/__init__.py
daft/ai/transformers/protocols/image_classifier.py
daft/ai/transformers/protocols/image_embedder.py
daft/ai/transformers/protocols/text_classifier.py
daft/ai/transformers/protocols/text_embedder.py
daft/ai/transformers/provider.py
daft/ai/typing.py
daft/ai/utils.py
daft/ai/vllm/protocols/prompter.py
daft/ai/vllm/provider.py
daft/api_annotations.py
daft/arrow_utils.py
daft/catalog/__glue.py
daft/catalog/__gravitino.py
daft/catalog/__iceberg.py
daft/catalog/__init__.py
daft/catalog/__internal.py
daft/catalog/__postgres.py
daft/catalog/__s3tables.py
daft/catalog/__unity.py
daft/cli.py
daft/context.py
daft/convert.py
daft/daft/__init__.pyi
daft/daft/dashboard.pyi
daft/daft/testing.pyi
daft/daft.abi3.so
daft/dataframe/__init__.py
daft/dataframe/dataframe.py
daft/dataframe/display.py
daft/dataframe/preview.py
daft/dataframe/to_torch.py
daft/datasets/__init__.py
daft/datasets/common_crawl.py
daft/datatype.py
daft/dependencies.py
daft/errors.py
daft/event_loop.py
daft/exceptions.py
daft/execution/__init__.py
daft/execution/native_executor.py
daft/execution/ray_actor_pool_udf.py
daft/execution/udf.py
daft/execution/udf_worker.py
daft/execution/vllm.py
daft/expressions/__init__.py
daft/expressions/expressions.py
daft/expressions/pyarrow_visitor.py
daft/expressions/testing.py
daft/expressions/visitor.py
daft_lts-0.7.2.dist-info/METADATA
daft_lts-0.7.2.dist-info/WHEEL
daft_lts-0.7.2.dist-info/entry_points.txt
daft_lts-0.7.2.dist-info/licenses/LICENSE
daft_lts-0.7.2.dist-info/RECORD
