Metadata-Version: 2.4
Name: daft-lts
Version: 0.7.2
Requires-Dist: pyarrow>=8.0.0,<23.0.0
Requires-Dist: fsspec<2025.11.0
Requires-Dist: tqdm<4.68.0
Requires-Dist: typing-extensions>=4.0.0 ; python_full_version < '3.11'
Requires-Dist: packaging
Requires-Dist: daft[aws,azure,clickhouse,deltalake,gcp,google,hudi,huggingface,iceberg,lance,numpy,openai,pandas,postgres,ray,sentence-transformers,sql,transformers,turbopuffer,unity,video] ; extra == 'all'
Requires-Dist: soundfile>=0.13.0,<0.14.0 ; extra == 'audio'
Requires-Dist: librosa>=0.11.0,<0.12.0 ; extra == 'audio'
Requires-Dist: boto3<1.43.0 ; extra == 'aws'
Requires-Dist: clickhouse-connect<0.11.0 ; extra == 'clickhouse'
Requires-Dist: deltalake<1.3.0 ; extra == 'deltalake'
Requires-Dist: google-genai<1.53.0 ; extra == 'google'
Requires-Dist: numpy<2.4.0 ; extra == 'google'
Requires-Dist: pillow==11.0.0 ; extra == 'google'
Requires-Dist: pyarrow>=8.0.0,<22.1.0 ; extra == 'hudi'
Requires-Dist: huggingface-hub<1.2.0 ; extra == 'huggingface'
Requires-Dist: datasets<4.5.0 ; extra == 'huggingface'
Requires-Dist: pyiceberg>=0.7.0,<0.9.1 ; extra == 'iceberg'
Requires-Dist: pylance<0.40.0 ; extra == 'lance'
Requires-Dist: numpy<2.4.0 ; extra == 'numpy'
Requires-Dist: openai<2.9.0 ; extra == 'openai'
Requires-Dist: numpy<2.4.0 ; extra == 'openai'
Requires-Dist: pillow==11.0.0 ; extra == 'openai'
Requires-Dist: pandas<2.4.0 ; extra == 'pandas'
Requires-Dist: psycopg[binary]<3.4.0 ; extra == 'postgres'
Requires-Dist: pgvector<0.5.0 ; extra == 'postgres'
Requires-Dist: sqlglot<28.1.0 ; extra == 'postgres'
Requires-Dist: connectorx>=0.4.4,<0.5.0 ; extra == 'postgres'
Requires-Dist: ray[data,client]>=2.0.0,<2.53.0 ; platform_system != 'Windows' and extra == 'ray'
Requires-Dist: ray[data,client]>=2.10.0,<2.53.0 ; platform_system == 'Windows' and extra == 'ray'
Requires-Dist: connectorx>=0.4.4,<0.5.0 ; extra == 'sql'
Requires-Dist: sqlalchemy<2.1.0 ; extra == 'sql'
Requires-Dist: sqlglot<28.1.0 ; extra == 'sql'
Requires-Dist: transformers<4.58.0 ; extra == 'transformers'
Requires-Dist: sentence-transformers<5.2.0 ; extra == 'transformers'
Requires-Dist: torch<2.10.0 ; extra == 'transformers'
Requires-Dist: torchvision<0.25.0 ; extra == 'transformers'
Requires-Dist: pillow==11.0.0 ; extra == 'transformers'
Requires-Dist: turbopuffer<1.9.0 ; extra == 'turbopuffer'
Requires-Dist: httpx<=0.27.2 ; extra == 'unity'
Requires-Dist: unitycatalog<0.2.0 ; extra == 'unity'
Requires-Dist: deltalake<1.3.0 ; extra == 'unity'
Requires-Dist: av>=15.0.0,<16.1.0 ; extra == 'video'
Provides-Extra: all
Provides-Extra: audio
Provides-Extra: aws
Provides-Extra: azure
Provides-Extra: clickhouse
Provides-Extra: deltalake
Provides-Extra: gcp
Provides-Extra: google
Provides-Extra: hudi
Provides-Extra: huggingface
Provides-Extra: iceberg
Provides-Extra: lance
Provides-Extra: numpy
Provides-Extra: openai
Provides-Extra: pandas
Provides-Extra: postgres
Provides-Extra: ray
Provides-Extra: sql
Provides-Extra: transformers
Provides-Extra: turbopuffer
Provides-Extra: unity
Provides-Extra: video
Provides-Extra: viz
License-File: LICENSE
Summary: Distributed Dataframes for Multimodal Data
Author-email: Eventual Inc <daft@eventualcomputing.com>
Maintainer-email: Sammy Sidhu <sammy@eventualcomputing.com>, Jay Chia <jay@eventualcomputing.com>
Requires-Python: >=3.10
Project-URL: homepage, https://www.daft.ai
Project-URL: repository, https://github.com/Eventual-Inc/Daft
